{
	"info": {
		"_postman_id": "a5bccada-518a-41fa-acf3-062a9e1bcdb4",
		"name": "COLLECT-DATA",
		"schema": "https://schema.getpostman.com/json/collection/v2.1.0/collection.json"
	},
	"item": [
		{
			"name": "ADD",
			"request": {
				"method": "POST",
				"header": [],
				"body": {
					"mode": "raw",
					"raw": "{\r\n    \"username\" : \"upfollowers.gacor\"\r\n}",
					"options": {
						"raw": {
							"language": "json"
						}
					}
				},
				"url": {
					"raw": "http://localhost:2039/api/add",
					"protocol": "http",
					"host": [
						"localhost"
					],
					"port": "2039",
					"path": [
						"api",
						"add"
					]
				}
			},
			"response": []
		},
		{
			"name": "NON ACTIVE",
			"request": {
				"method": "POST",
				"header": [],
				"body": {
					"mode": "raw",
					"raw": "{\r\n    \"username\" : \"upfollowers.gacor\"\r\n}",
					"options": {
						"raw": {
							"language": "json"
						}
					}
				},
				"url": {
					"raw": "http://localhost:2039/api/non-active",
					"protocol": "http",
					"host": [
						"localhost"
					],
					"port": "2039",
					"path": [
						"api",
						"non-active"
					]
				}
			},
			"response": []
		},
		{
			"name": "ACTIVE",
			"request": {
				"method": "POST",
				"header": [],
				"body": {
					"mode": "raw",
					"raw": "{\r\n    \"username\" : \"upfollowers.gacor\"\r\n}",
					"options": {
						"raw": {
							"language": "json"
						}
					}
				},
				"url": {
					"raw": "http://localhost:2039/api/active",
					"protocol": "http",
					"host": [
						"localhost"
					],
					"port": "2039",
					"path": [
						"api",
						"active"
					]
				}
			},
			"response": []
		},
		{
			"name": "CHATS",
			"request": {
				"method": "POST",
				"header": [],
				"body": {
					"mode": "raw",
					"raw": "{\r\n    \"limit\" : 100,\r\n    \"username\" : \"upfollowers.gacor\"\r\n}",
					"options": {
						"raw": {
							"language": "json"
						}
					}
				},
				"url": {
					"raw": "http://localhost:2039/api/chats",
					"protocol": "http",
					"host": [
						"localhost"
					],
					"port": "2039",
					"path": [
						"api",
						"chats"
					]
				}
			},
			"response": []
		},
		{
			"name": "GIFTS",
			"request": {
				"method": "POST",
				"header": [],
				"body": {
					"mode": "raw",
					"raw": "{\r\n    \"limit\" : 100,\r\n    \"username\" : \"upfollowers.gacor\"\r\n}",
					"options": {
						"raw": {
							"language": "json"
						}
					}
				},
				"url": {
					"raw": "http://localhost:2039/api/gifts",
					"protocol": "http",
					"host": [
						"localhost"
					],
					"port": "2039",
					"path": [
						"api",
						"gifts"
					]
				}
			},
			"response": []
		}
	]
}